dbl_stress_template/__init__.py
dbl_stress_template/canonical.py
dbl_stress_template/cli.py
dbl_stress_template/model.py
dbl_stress_template/runner.py
dbl_stress_template-0.1.0.dist-info/licenses/LICENSE
dbl_stress_template-0.1.0.dist-info/METADATA
dbl_stress_template-0.1.0.dist-info/WHEEL
dbl_stress_template-0.1.0.dist-info/top_level.txt
dbl_stress_template-0.1.0.dist-info/RECORD
