Metadata-Version: 2.4
Name: dbl-stress-template
Version: 0.1.0
Summary: Minimal DBL stress-case runner for deterministic event streams
License: MIT
Requires-Python: >=3.11
License-File: LICENSE
Requires-Dist: dbl-core<0.4.0,>=0.3.2
Requires-Dist: pyyaml>=6.0.1
Dynamic: license-file
